{
    "id": "01984ff5-732c-746c-905b-275d4ae11d26",
    "memberId": "0197e5b5-7ce0-7bf3-87d1-f1d50963bc9c",
    "type": "ms_getpdf",
    "fileName": "0198a41c-2672-700d-a860-636cd5636e59",
    "editedPDF": "MobileSurvey/EditedPDF/0197d120-14a2-71c2-8805-36d3a653dff6/0198a41c-2672-700d-a860-68f93279754b.pdf",
    "data": "{\"data\":{\"District\":\"COIMBATORE\",\"Survey_No\":\"259\",\"Taluk\":\"Coimbatore North\",\"Village\":\"Saravanampatty.\",\"duppoints\":[{\"id\":1,\"key\":\"F\",\"latitude\":718526.08,\"latstatus\":\"notmodified\",\"longitude\":1224091.353,\"longstatus\":\"notmodified\"},{\"id\":2,\"key\":\"E\",\"latitude\":718589.056,\"latstatus\":\"notmodified\",\"longitude\":1224153.72,\"longstatus\":\"notmodified\"},{\"id\":3,\"key\":\"D\",\"latitude\":718635.146,\"latstatus\":\"notmodified\",\"longitude\":1224213.247,\"longstatus\":\"notmodified\"},{\"id\":4,\"key\":\"C\",\"latitude\":718680.527,\"latstatus\":\"notmodified\",\"longitude\":1224212.248,\"longstatus\":\"notmodified\"},{\"id\":5,\"key\":\"B\",\"latitude\":718569.083,\"latstatus\":\"notmodified\",\"longitude\":1223956.011,\"longstatus\":\"notmodified\"},{\"id\":6,\"key\":\"A\",\"latitude\":718533.011,\"latstatus\":\"notmodified\",\"longitude\":1224004.479,\"longstatus\":\"notmodified\"},{\"id\":7,\"key\":\"131\",\"latitude\":718617.325,\"latstatus\":\"notmodified\",\"longitude\":1224086.675,\"longstatus\":\"notmodified\"},{\"id\":8,\"key\":\"63\",\"latitude\":718597.882,\"latstatus\":\"notmodified\",\"longitude\":1224101.712,\"longstatus\":\"notmodified\"},{\"id\":9,\"key\":\"53\",\"latitude\":718575.051,\"latstatus\":\"notmodified\",\"longitude\":1224122.92,\"longstatus\":\"notmodified\"},{\"id\":10,\"key\":\"42\",\"latitude\":718592.874,\"latstatus\":\"notmodified\",\"longitude\":1224145.284,\"longstatus\":\"notmodified\"},{\"id\":11,\"key\":\"41\",\"latitude\":718597.085,\"latstatus\":\"notmodified\",\"longitude\":1224164.093,\"longstatus\":\"notmodified\"},{\"id\":12,\"key\":\"40\",\"latitude\":718608.736,\"latstatus\":\"notmodified\",\"longitude\":1224179.138,\"longstatus\":\"notmodified\"},{\"id\":13,\"key\":\"39\",\"latitude\":718620.94,\"latstatus\":\"notmodified\",\"longitude\":1224194.941,\"longstatus\":\"notmodified\"},{\"id\":14,\"key\":\"38\",\"latitude\":718653.711,\"latstatus\":\"notmodified\",\"longitude\":1224167.354,\"longstatus\":\"notmodified\"},{\"id\":15,\"key\":\"37\",\"latitude\":718644.187,\"latstatus\":\"notmodified\",\"longitude\":1224147.266,\"longstatus\":\"notmodified\"},{\"id\":16,\"key\":\"36\",\"latitude\":718635.817,\"latstatus\":\"notmodified\",\"longitude\":1224129.412,\"longstatus\":\"notmodified\"},{\"id\":17,\"key\":\"35\",\"latitude\":718631.067,\"latstatus\":\"notmodified\",\"longitude\":1224119.547,\"longstatus\":\"notmodified\"},{\"id\":18,\"key\":\"34\",\"latitude\":718625.623,\"latstatus\":\"notmodified\",\"longitude\":1224106.77,\"longstatus\":\"notmodified\"},{\"id\":19,\"key\":\"33\",\"latitude\":718609.908,\"latstatus\":\"notmodified\",\"longitude\":1224069.047,\"longstatus\":\"notmodified\"},{\"id\":20,\"key\":\"32\",\"latitude\":718603.068,\"latstatus\":\"notmodified\",\"longitude\":1224052.537,\"longstatus\":\"notmodified\"},{\"id\":21,\"key\":\"31\",\"latitude\":718587.36,\"latstatus\":\"notmodified\",\"longitude\":1224008.79,\"longstatus\":\"notmodified\"},{\"id\":22,\"key\":\"30\",\"latitude\":718558.828,\"latstatus\":\"notmodified\",\"longitude\":1223969.768,\"longstatus\":\"notmodified\"},{\"id\":23,\"key\":\"10\",\"latitude\":718602.006,\"latstatus\":\"notmodified\",\"longitude\":1224098.559,\"longstatus\":\"notmodified\"},{\"id\":24,\"key\":\"9\",\"latitude\":718614.817,\"latstatus\":\"notmodified\",\"longitude\":1224080.813,\"longstatus\":\"notmodified\"},{\"id\":25,\"key\":\"8\",\"latitude\":718599.815,\"latstatus\":\"notmodified\",\"longitude\":1224092.569,\"longstatus\":\"notmodified\"},{\"id\":26,\"key\":\"7\",\"latitude\":718554.658,\"latstatus\":\"notmodified\",\"longitude\":1224102.092,\"longstatus\":\"notmodified\"},{\"id\":27,\"key\":\"6\",\"latitude\":718587.615,\"latstatus\":\"notmodified\",\"longitude\":1224138.699,\"longstatus\":\"notmodified\"},{\"id\":28,\"key\":\"5\",\"latitude\":718595.941,\"latstatus\":\"notmodified\",\"longitude\":1224149.198,\"longstatus\":\"notmodified\"},{\"id\":29,\"key\":\"4\",\"latitude\":718580.082,\"latstatus\":\"notmodified\",\"longitude\":1224072.456,\"longstatus\":\"notmodified\"},{\"id\":30,\"key\":\"3\",\"latitude\":718588.488,\"latstatus\":\"notmodified\",\"longitude\":1224085.871,\"longstatus\":\"notmodified\"},{\"id\":31,\"key\":\"2\",\"latitude\":718599.465,\"latstatus\":\"notmodified\",\"longitude\":1224043.68,\"longstatus\":\"notmodified\"},{\"id\":32,\"key\":\"1\",\"latitude\":718629.889,\"latstatus\":\"notmodified\",\"longitude\":1224116.954,\"longstatus\":\"notmodified\"}],\"lines\":[{\"coordinates\":[\"A\",\"30\"],\"dashes\":\"[ 9 0 ] 1\",\"length\":380.04474,\"strokewidth\":\"3\"},{\"coordinates\":[\"30\",\"B\"],\"dashes\":\"[ 9 0 ] 1\",\"length\":150.74814,\"strokewidth\":\"3\"},{\"coordinates\":[\"B\",\"31\"],\"dashes\":\"[ 9 0 ] 1\",\"length\":490.6893,\"strokewidth\":\"3\"},{\"coordinates\":[\"31\",\"2\"],\"dashes\":\"[ 9 0 ] 1\",\"length\":324.44568,\"strokewidth\":\"3\"},{\"coordinates\":[\"2\",\"32\"],\"dashes\":\"[ 9 0 ] 1\",\"length\":84,\"strokewidth\":\"3\"},{\"coordinates\":[\"32\",\"33\"],\"dashes\":\"[ 9 0 ] 1\",\"length\":157.00319,\"strokewidth\":\"3\"},{\"coordinates\":[\"34\",\"1\"],\"dashes\":\"[ 9 0 ] 1\",\"length\":97.00516,\"strokewidth\":\"3\"},{\"coordinates\":[\"1\",\"35\"],\"dashes\":\"[ 9 0 ] 1\",\"length\":25.019993,\"strokewidth\":\"3\"},{\"coordinates\":[\"35\",\"36\"],\"dashes\":\"[ 9 0 ] 1\",\"length\":96.18732,\"strokewidth\":\"3\"},{\"coordinates\":[\"36\",\"37\"],\"dashes\":\"[ 9 0 ] 1\",\"length\":173.23395,\"strokewidth\":\"3\"},{\"coordinates\":[\"37\",\"38\"],\"dashes\":\"[ 9 0 ] 1\",\"length\":195.31001,\"strokewidth\":\"3\"},{\"coordinates\":[\"38\",\"C\"],\"dashes\":\"[ 9 0 ] 1\",\"length\":205.2949,\"strokewidth\":\"3\"},{\"coordinates\":[\"C\",\"D\"],\"dashes\":\"[ 9 0 ] 1\",\"length\":331.73032,\"strokewidth\":\"3\"},{\"coordinates\":[\"D\",\"39\"],\"dashes\":\"[ 9 0 ] 1\",\"length\":203.57063,\"strokewidth\":\"3\"},{\"coordinates\":[\"39\",\"40\"],\"dashes\":\"[ 9 0 ] 1\",\"length\":175.4138,\"strokewidth\":\"3\"},{\"coordinates\":[\"40\",\"41\"],\"dashes\":\"[ 9 0 ] 1\",\"length\":167.17058,\"strokewidth\":\"3\"},{\"coordinates\":[\"41\",\"E\"],\"dashes\":\"[ 9 0 ] 1\",\"length\":115.24756,\"strokewidth\":\"3\"},{\"coordinates\":[\"E\",\"F\"],\"dashes\":\"[ 9 0 ] 1\",\"length\":778.6475,\"strokewidth\":\"3\"},{\"coordinates\":[\"F\",\"A\"],\"dashes\":\"[ 9 0 ] 1\",\"length\":765.6318,\"strokewidth\":\"3\"},{\"coordinates\":[\"131\",\"34\"],\"dashes\":\"[ 9 0 ] 1\",\"length\":191.00262,\"strokewidth\":\"3\"},{\"coordinates\":[\"33\",\"9\"],\"dashes\":\"[ 9 0 ] 1\",\"length\":112.00446,\"strokewidth\":\"3\"},{\"coordinates\":[\"9\",\"131\"],\"dashes\":\"[ 9 0 ] 1\",\"length\":56.008926,\"strokewidth\":\"3\"},{\"coordinates\":[\"C\",\"B\"],\"dashes\":\"[ 30 10 1 3 1 3 1 10 ] 1\",\"length\":2205,\"strokewidth\":\"2\"},{\"coordinates\":[\"A\",\"C\"],\"dashes\":\"[ 30 10 1 3 1 3 1 10 ] 1\",\"length\":1982.679,\"strokewidth\":\"2\"},{\"coordinates\":[\"C\",\"E\"],\"dashes\":\"[ 30 10 1 3 1 3 1 10 ] 1\",\"length\":723.1625,\"strokewidth\":\"2\"},{\"coordinates\":[\"E\",\"A\"],\"dashes\":\"[ 30 10 1 3 1 3 1 10 ] 1\",\"length\":1400.5156,\"strokewidth\":\"2\"},{\"coordinates\":[\"D\",\"E\"],\"dashes\":\"[ 30 10 1 3 1 3 1 10 ] 1\",\"length\":661.4023,\"strokewidth\":\"2\"},{\"coordinates\":[\"36\",\"37\"],\"dashes\":\"[ 9 0 ] 1\",\"length\":173.23395,\"strokewidth\":\"2\"},{\"coordinates\":[\"37\",\"40\"],\"dashes\":\"[ 9 0 ] 1\",\"length\":418.80783,\"strokewidth\":\"2\"},{\"coordinates\":[\"40\",\"41\"],\"dashes\":\"[ 9 0 ] 1\",\"length\":167.17058,\"strokewidth\":\"2\"},{\"coordinates\":[\"41\",\"36\"],\"dashes\":\"[ 9 0 ] 1\",\"length\":456.745,\"strokewidth\":\"2\"},{\"coordinates\":[\"32\",\"33\"],\"dashes\":\"[ 9 0 ] 1\",\"length\":157.00319,\"strokewidth\":\"2\"},{\"coordinates\":[\"33\",\"3\"],\"dashes\":\"[ 9 0 ] 1\",\"length\":239.28226,\"strokewidth\":\"2\"},{\"coordinates\":[\"3\",\"4\"],\"dashes\":\"[ 9 0 ] 1\",\"length\":139.0863,\"strokewidth\":\"2\"},{\"coordinates\":[\"4\",\"32\"],\"dashes\":\"[ 9 0 ] 1\",\"length\":267.21713,\"strokewidth\":\"2\"},{\"coordinates\":[\"37\",\"38\"],\"dashes\":\"[ 9 0 ] 1\",\"length\":195.31001,\"strokewidth\":\"2\"},{\"coordinates\":[\"38\",\"39\"],\"dashes\":\"[ 9 0 ] 1\",\"length\":376.32434,\"strokewidth\":\"2\"},{\"coordinates\":[\"39\",\"40\"],\"dashes\":\"[ 9 0 ] 1\",\"length\":175.4138,\"strokewidth\":\"2\"},{\"coordinates\":[\"40\",\"37\"],\"dashes\":\"[ 9 0 ] 1\",\"length\":418.80783,\"strokewidth\":\"2\"},{\"coordinates\":[\"B\",\"31\"],\"dashes\":\"[ 9 0 ] 1\",\"length\":490.6893,\"strokewidth\":\"2\"},{\"coordinates\":[\"31\",\"30\"],\"dashes\":\"[ 9 0 ] 1\",\"length\":424.67987,\"strokewidth\":\"2\"},{\"coordinates\":[\"30\",\"B\"],\"dashes\":\"[ 9 0 ] 1\",\"length\":150.74814,\"strokewidth\":\"2\"},{\"coordinates\":[\"33\",\"9\"],\"dashes\":\"[ 9 0 ] 1\",\"length\":112.00446,\"strokewidth\":\"2\"},{\"coordinates\":[\"9\",\"8\"],\"dashes\":\"[ 9 0 ] 1\",\"length\":167.44252,\"strokewidth\":\"2\"},{\"coordinates\":[\"8\",\"10\"],\"dashes\":\"[ 9 0 ] 1\",\"length\":56.0357,\"strokewidth\":\"2\"},{\"coordinates\":[\"10\",\"63\"],\"dashes\":\"[ 9 0 ] 1\",\"length\":45.607018,\"strokewidth\":\"2\"},{\"coordinates\":[\"63\",\"3\"],\"dashes\":\"[ 9 0 ] 1\",\"length\":161.79,\"strokewidth\":\"2\"},{\"coordinates\":[\"3\",\"33\"],\"dashes\":\"[ 9 0 ] 1\",\"length\":239.28226,\"strokewidth\":\"2\"},{\"coordinates\":[\"63\",\"3\"],\"dashes\":\"[ 9 0 ] 1\",\"length\":161.79,\"strokewidth\":\"2\"},{\"coordinates\":[\"3\",\"4\"],\"dashes\":\"[ 9 0 ] 1\",\"length\":139.0863,\"strokewidth\":\"2\"},{\"coordinates\":[\"4\",\"7\"],\"dashes\":\"[ 9 0 ] 1\",\"length\":343.03644,\"strokewidth\":\"2\"},{\"coordinates\":[\"7\",\"53\"],\"dashes\":\"[ 9 0 ] 1\",\"length\":256.08203,\"strokewidth\":\"2\"},{\"coordinates\":[\"53\",\"63\"],\"dashes\":\"[ 9 0 ] 1\",\"length\":273.76083,\"strokewidth\":\"2\"},{\"coordinates\":[\"1\",\"35\"],\"dashes\":\"[ 9 0 ] 1\",\"length\":25.019993,\"strokewidth\":\"2\"},{\"coordinates\":[\"35\",\"5\"],\"dashes\":\"[ 9 0 ] 1\",\"length\":403.8329,\"strokewidth\":\"2\"},{\"coordinates\":[\"5\",\"42\"],\"dashes\":\"[ 9 0 ] 1\",\"length\":43.68066,\"strokewidth\":\"2\"},{\"coordinates\":[\"42\",\"6\"],\"dashes\":\"[ 9 0 ] 1\",\"length\":74.04053,\"strokewidth\":\"2\"},{\"coordinates\":[\"6\",\"34\"],\"dashes\":\"[ 9 0 ] 1\",\"length\":436.09747,\"strokewidth\":\"2\"},{\"coordinates\":[\"34\",\"1\"],\"dashes\":\"[ 9 0 ] 1\",\"length\":97.00516,\"strokewidth\":\"2\"},{\"coordinates\":[\"36\",\"41\"],\"dashes\":\"[ 9 0 ] 1\",\"length\":456.745,\"strokewidth\":\"2\"},{\"coordinates\":[\"41\",\"E\"],\"dashes\":\"[ 9 0 ] 1\",\"length\":115.24756,\"strokewidth\":\"2\"},{\"coordinates\":[\"E\",\"42\"],\"dashes\":\"[ 9 0 ] 1\",\"length\":81.34495,\"strokewidth\":\"2\"},{\"coordinates\":[\"42\",\"5\"],\"dashes\":\"[ 9 0 ] 1\",\"length\":43.68066,\"strokewidth\":\"2\"},{\"coordinates\":[\"5\",\"35\"],\"dashes\":\"[ 9 0 ] 1\",\"length\":403.8329,\"strokewidth\":\"2\"},{\"coordinates\":[\"35\",\"36\"],\"dashes\":\"[ 9 0 ] 1\",\"length\":96.18732,\"strokewidth\":\"2\"},{\"coordinates\":[\"38\",\"C\"],\"dashes\":\"[ 9 0 ] 1\",\"length\":205.2949,\"strokewidth\":\"2\"},{\"coordinates\":[\"C\",\"D\"],\"dashes\":\"[ 9 0 ] 1\",\"length\":331.73032,\"strokewidth\":\"2\"},{\"coordinates\":[\"D\",\"39\"],\"dashes\":\"[ 9 0 ] 1\",\"length\":203.57063,\"strokewidth\":\"2\"},{\"coordinates\":[\"39\",\"38\"],\"dashes\":\"[ 9 0 ] 1\",\"length\":376.32434,\"strokewidth\":\"2\"},{\"coordinates\":[\"31\",\"2\"],\"dashes\":\"[ 9 0 ] 1\",\"length\":324.44568,\"strokewidth\":\"2\"},{\"coordinates\":[\"2\",\"32\"],\"dashes\":\"[ 9 0 ] 1\",\"length\":84,\"strokewidth\":\"2\"},{\"coordinates\":[\"32\",\"4\"],\"dashes\":\"[ 9 0 ] 1\",\"length\":267.21713,\"strokewidth\":\"2\"},{\"coordinates\":[\"4\",\"7\"],\"dashes\":\"[ 9 0 ] 1\",\"length\":343.03644,\"strokewidth\":\"2\"},{\"coordinates\":[\"7\",\"53\"],\"dashes\":\"[ 9 0 ] 1\",\"length\":256.08203,\"strokewidth\":\"2\"},{\"coordinates\":[\"53\",\"63\"],\"dashes\":\"[ 9 0 ] 1\",\"length\":273.76083,\"strokewidth\":\"2\"},{\"coordinates\":[\"63\",\"10\"],\"dashes\":\"[ 9 0 ] 1\",\"length\":45.607018,\"strokewidth\":\"2\"},{\"coordinates\":[\"10\",\"131\"],\"dashes\":\"[ 9 0 ] 1\",\"length\":170.32909,\"strokewidth\":\"2\"},{\"coordinates\":[\"131\",\"34\"],\"dashes\":\"[ 9 0 ] 1\",\"length\":191.00262,\"strokewidth\":\"2\"},{\"coordinates\":[\"34\",\"6\"],\"dashes\":\"[ 9 0 ] 1\",\"length\":436.09747,\"strokewidth\":\"2\"},{\"coordinates\":[\"6\",\"42\"],\"dashes\":\"[ 9 0 ] 1\",\"length\":74.04053,\"strokewidth\":\"2\"},{\"coordinates\":[\"42\",\"E\"],\"dashes\":\"[ 9 0 ] 1\",\"length\":81.34495,\"strokewidth\":\"2\"},{\"coordinates\":[\"E\",\"F\"],\"dashes\":\"[ 9 0 ] 1\",\"length\":778.6475,\"strokewidth\":\"2\"},{\"coordinates\":[\"F\",\"A\"],\"dashes\":\"[ 9 0 ] 1\",\"length\":765.6318,\"strokewidth\":\"2\"},{\"coordinates\":[\"A\",\"30\"],\"dashes\":\"[ 9 0 ] 1\",\"length\":380.04474,\"strokewidth\":\"2\"},{\"coordinates\":[\"30\",\"31\"],\"dashes\":\"[ 9 0 ] 1\",\"length\":424.67987,\"strokewidth\":\"2\"}],\"points\":[{\"id\":1,\"key\":\"F\",\"latitude\":11.066739532286645,\"latstatus\":\"notmodified\",\"longitude\":77.00042380401912,\"longstatus\":\"notmodified\"},{\"id\":2,\"key\":\"E\",\"latitude\":11.0672994144109,\"latstatus\":\"notmodified\",\"longitude\":77.00100387962219,\"longstatus\":\"notmodified\"},{\"id\":3,\"key\":\"D\",\"latitude\":11.067834649850505,\"latstatus\":\"notmodified\",\"longitude\":77.0014292708869,\"longstatus\":\"notmodified\"},{\"id\":4,\"key\":\"C\",\"latitude\":11.067822868501043,\"latstatus\":\"notmodified\",\"longitude\":77.00184445986926,\"longstatus\":\"notmodified\"},{\"id\":5,\"key\":\"B\",\"latitude\":11.065513648448944,\"latstatus\":\"notmodified\",\"longitude\":77.00080898944746,\"longstatus\":\"notmodified\"},{\"id\":6,\"key\":\"A\",\"latitude\":11.065953908547487,\"latstatus\":\"notmodified\",\"longitude\":77.00048189504729,\"longstatus\":\"notmodified\"},{\"id\":7,\"key\":\"131\",\"latitude\":11.06669172007509,\"latstatus\":\"notmodified\",\"longitude\":77.00125843445225,\"longstatus\":\"notmodified\"},{\"id\":8,\"key\":\"63\",\"latitude\":11.066828809406337,\"latstatus\":\"notmodified\",\"longitude\":77.00108144837782,\"longstatus\":\"notmodified\"},{\"id\":9,\"key\":\"53\",\"latitude\":11.067021880098105,\"latstatus\":\"notmodified\",\"longitude\":77.00087383962904,\"longstatus\":\"notmodified\"},{\"id\":10,\"key\":\"42\",\"latitude\":11.067222934880744,\"latstatus\":\"notmodified\",\"longitude\":77.00103829774048,\"longstatus\":\"notmodified\"},{\"id\":11,\"key\":\"41\",\"latitude\":11.067392683180733,\"latstatus\":\"notmodified\",\"longitude\":77.00107798398928,\"longstatus\":\"notmodified\"},{\"id\":12,\"key\":\"40\",\"latitude\":11.067527959816022,\"latstatus\":\"notmodified\",\"longitude\":77.00118551755848,\"longstatus\":\"notmodified\"},{\"id\":13,\"key\":\"39\",\"latitude\":11.067670053984626,\"latstatus\":\"notmodified\",\"longitude\":77.00129815787835,\"longstatus\":\"notmodified\"},{\"id\":14,\"key\":\"38\",\"latitude\":11.067418724205861,\"latstatus\":\"notmodified\",\"longitude\":77.00159632907648,\"longstatus\":\"notmodified\"},{\"id\":15,\"key\":\"37\",\"latitude\":11.067237738050546,\"latstatus\":\"notmodified\",\"longitude\":77.00150794850767,\"longstatus\":\"notmodified\"},{\"id\":16,\"key\":\"36\",\"latitude\":11.067076873698431,\"latstatus\":\"notmodified\",\"longitude\":77.00143026462322,\"longstatus\":\"notmodified\"},{\"id\":17,\"key\":\"35\",\"latitude\":11.066987997731287,\"latstatus\":\"notmodified\",\"longitude\":77.00138619523052,\"longstatus\":\"notmodified\"},{\"id\":18,\"key\":\"34\",\"latitude\":11.066872843962983,\"latstatus\":\"notmodified\",\"longitude\":77.00133559683835,\"longstatus\":\"notmodified\"},{\"id\":19,\"key\":\"33\",\"latitude\":11.066532840514885,\"latstatus\":\"notmodified\",\"longitude\":77.00118948497128,\"longstatus\":\"notmodified\"},{\"id\":20,\"key\":\"32\",\"latitude\":11.066384030897595,\"latstatus\":\"notmodified\",\"longitude\":77.00112588389278,\"longstatus\":\"notmodified\"},{\"id\":21,\"key\":\"31\",\"latitude\":11.065989579400757,\"latstatus\":\"notmodified\",\"longitude\":77.00097946700078,\"longstatus\":\"notmodified\"},{\"id\":22,\"key\":\"30\",\"latitude\":11.065638611464378,\"latstatus\":\"notmodified\",\"longitude\":77.0007159976929,\"longstatus\":\"notmodified\"},{\"id\":23,\"key\":\"10\",\"latitude\":11.066800061282729,\"latstatus\":\"notmodified\",\"longitude\":77.00111899064756,\"longstatus\":\"notmodified\"},{\"id\":24,\"key\":\"9\",\"latitude\":11.066638888925091,\"latstatus\":\"notmodified\",\"longitude\":77.00123512578159,\"longstatus\":\"notmodified\"},{\"id\":25,\"key\":\"8\",\"latitude\":11.06674605398579,\"latstatus\":\"notmodified\",\"longitude\":77.0010985747719,\"longstatus\":\"notmodified\"},{\"id\":26,\"key\":\"7\",\"latitude\":11.066834863957347,\"latstatus\":\"notmodified\",\"longitude\":77.0006859597605,\"longstatus\":\"notmodified\"},{\"id\":27,\"key\":\"6\",\"latitude\":11.067163735702763,\"latstatus\":\"notmodified\",\"longitude\":77.00098977221549,\"longstatus\":\"notmodified\"},{\"id\":28,\"key\":\"5\",\"latitude\":11.06725812531956,\"latstatus\":\"notmodified\",\"longitude\":77.00106660190812,\"longstatus\":\"notmodified\"},{\"id\":29,\"key\":\"4\",\"latitude\":11.066565460440167,\"latstatus\":\"notmodified\",\"longitude\":77.00091677805005,\"longstatus\":\"notmodified\"},{\"id\":30,\"key\":\"3\",\"latitude\":11.066686201285675,\"latstatus\":\"notmodified\",\"longitude\":77.00099451849812,\"longstatus\":\"notmodified\"},{\"id\":31,\"key\":\"2\",\"latitude\":11.06630419604512,\"latstatus\":\"notmodified\",\"longitude\":77.00109237193979,\"longstatus\":\"notmodified\"},{\"id\":32,\"key\":\"1\",\"latitude\":11.066964632542623,\"latstatus\":\"notmodified\",\"longitude\":77.00137525703497,\"longstatus\":\"notmodified\"}],\"subdivision_list\":{\"2\":[[718571.47,1223977.282],[\"B\",\"31\",\"30\",\"B\"],0],\"4\":[[718576.555,1224098.222],[\"63\",\"3\",\"4\",\"7\",\"53\",\"63\"],123456],\"1A2\":[[718609.554,1224127.685],[\"1\",\"35\",\"5\",\"42\",\"6\",\"34\",\"1\"],0],\"1A3\":[[718611.835,1224141.749],[\"36\",\"41\",\"E\",\"42\",\"5\",\"35\",\"36\"],0],\"1A4\":[[718620.996,1224153.997],[\"36\",\"37\",\"40\",\"41\",\"36\"],0],\"1AIB\":[[718595.111,1224068.923],[\"32\",\"33\",\"3\",\"4\",\"32\"],0],\"1B1\":[[718631.623,1224171.056],[\"37\",\"38\",\"39\",\"40\",\"37\"],0],\"1B2\":[[718642.873,1224189.951],[\"38\",\"C\",\"D\",\"39\",\"38\"],0],\"3A\":[[718573.7,1224036.835],[\"31\",\"2\",\"32\",\"4\",\"7\",\"53\",\"63\",\"10\",\"131\",\"34\",\"6\",\"42\",\"E\",\"F\",\"A\",\"30\",\"31\"],0],\"3B1\":[[718599.94,1224085.022],[\"33\",\"9\",\"8\",\"10\",\"63\",\"3\",\"33\"],0]}},\"id\":\"01984ff5-732c-746c-905b-275d4ae11d26\",\"memberId\":\"0197e5b5-7ce0-7bf3-87d1-f1d50963bc9c\",\"fileName\":\"0198a41c-2672-700d-a860-636cd5636e59\",\"editedPDF\":\"MobileSurvey/EditedPDF/0197d120-14a2-71c2-8805-36d3a653dff6/0198a41c-2672-700d-a860-68f93279754b.pdf\"}"
}