{"Scale": "1:258", "coordinates": {"1": [[718502.214, 1223914.316], "main", ["notmodified", "notmodified"]], "101": [[718455.737, 1223983.414], "main", ["notmodified", "notmodified"]], "102": [[718455.402, 1223977.404], "main", ["notmodified", "notmodified"]], "103": [[718454.956, 1223969.39], "main", ["notmodified", "notmodified"]], "104": [[718454.509, 1223961.377], "main", ["notmodified", "notmodified"]], "105": [[718454.174, 1223955.367], "main", ["notmodified", "notmodified"]], "106": [[718453.732, 1223947.445], "main", ["notmodified", "notmodified"]], "107": [[718453.286, 1223939.431], "main", ["notmodified", "notmodified"]], "108": [[718452.951, 1223933.421], "main", ["notmodified", "notmodified"]], "109": [[718452.504, 1223925.408], "main", ["notmodified", "notmodified"]], "110": [[718452.057, 1223917.394], "main", ["notmodified", "notmodified"]], "111": [[718451.722, 1223911.384], "main", ["notmodified", "notmodified"]], "112": [[718455.783, 1223903.941], "main", ["notmodified", "notmodified"]], "113": [[718465.704, 1223904.941], "main", ["notmodified", "notmodified"]], "114": [[718475.625, 1223905.941], "main", ["notmodified", "notmodified"]], "115": [[718485.551, 1223907.032], "main", ["notmodified", "notmodified"]], "116": [[718495.472, 1223908.032], "main", ["notmodified", "notmodified"]], "117": [[718498.69, 1223908.4], "main", ["notmodified", "notmodified"]], "118": [[718459.981, 1223977.605], "main", ["notmodified", "notmodified"]], "119": [[718469.962, 1223978.054], "main", ["notmodified", "notmodified"]], "120": [[718479.858, 1223978.598], "main", ["notmodified", "notmodified"]], "121": [[718489.749, 1223979.052], "main", ["notmodified", "notmodified"]], "122": [[718499.639, 1223979.505], "main", ["notmodified", "notmodified"]], "123": [[718509.535, 1223980.049], "main", ["notmodified", "notmodified"]], "124": [[718461.197, 1223961.735], "main", ["notmodified", "notmodified"]], "125": [[718471.184, 1223962.274], "main", ["notmodified", "notmodified"]], "126": [[718481.079, 1223962.819], "main", ["notmodified", "notmodified"]], "127": [[718491.061, 1223963.267], "main", ["notmodified", "notmodified"]], "128": [[718500.956, 1223963.812], "main", ["notmodified", "notmodified"]], "129": [[718510.943, 1223964.351], "main", ["notmodified", "notmodified"]], "130": [[718501.75, 1223958.378], "main", ["notmodified", "notmodified"]], "131": [[718491.758, 1223957.748], "main", ["notmodified", "notmodified"]], "132": [[718481.766, 1223957.117], "main", ["notmodified", "notmodified"]], "133": [[718471.683, 1223956.492], "main", ["notmodified", "notmodified"]], "134": [[718461.692, 1223955.861], "main", ["notmodified", "notmodified"]], "135": [[718510.319, 1223953.15], "main", ["notmodified", "notmodified"]], "136": [[718462.913, 1223940.082], "main", ["notmodified", "notmodified"]], "137": [[718472.819, 1223940.808], "main", ["notmodified", "notmodified"]], "138": [[718482.719, 1223941.444], "main", ["notmodified", "notmodified"]], "139": [[718492.625, 1223942.171], "main", ["notmodified", "notmodified"]], "140": [[718502.435, 1223942.811], "main", ["notmodified", "notmodified"]], "151": [[718501.427, 1223936.199], "main", ["notmodified", "notmodified"]], "152": [[718493.363, 1223935.735], "main", ["notmodified", "notmodified"]], "153": [[718494.796, 1223915.56], "main", ["notmodified", "notmodified"]], "154": [[718484.875, 1223914.56], "main", ["notmodified", "notmodified"]], "155": [[718474.959, 1223913.651], "main", ["notmodified", "notmodified"]], "156": [[718465.043, 1223912.742], "main", ["notmodified", "notmodified"]], "157": [[718455.122, 1223911.743], "main", ["notmodified", "notmodified"]], "158": [[718510.191, 1223972.157], "main", ["notmodified", "notmodified"]], "159": [[718500.3, 1223971.704], "main", ["notmodified", "notmodified"]], "160": [[718490.405, 1223971.159], "main", ["notmodified", "notmodified"]], "161": [[718480.423, 1223970.711], "main", ["notmodified", "notmodified"]], "162": [[718470.528, 1223970.166], "main", ["notmodified", "notmodified"]], "163": [[718460.546, 1223969.718], "main", ["notmodified", "notmodified"]], "164": [[718501.976, 1223952.611], "main", ["notmodified", "notmodified"]], "165": [[718502.138, 1223950.592], "main", ["notmodified", "notmodified"]], "166": [[718492.146, 1223949.962], "main", ["notmodified", "notmodified"]], "167": [[718482.245, 1223949.326], "main", ["notmodified", "notmodified"]], "168": [[718472.249, 1223948.605], "main", ["notmodified", "notmodified"]], "169": [[718462.348, 1223947.969], "main", ["notmodified", "notmodified"]], "171": [[718483.376, 1223935.196], "main", ["notmodified", "notmodified"]], "172": [[718473.293, 1223934.571], "main", ["notmodified", "notmodified"]], "173": [[718463.307, 1223934.031], "main", ["notmodified", "notmodified"]], "174": [[718453.315, 1223933.401], "main", ["notmodified", "notmodified"]], "175": [[718504.294, 1223928.641], "main", ["notmodified", "notmodified"]], "176": [[718494.302, 1223928.01], "main", ["notmodified", "notmodified"]], "177": [[718484.219, 1223927.385], "main", ["notmodified", "notmodified"]], "178": [[718474.228, 1223926.754], "main", ["notmodified", "notmodified"]], "179": [[718464.236, 1223926.124], "main", ["notmodified", "notmodified"]], "180": [[718454.244, 1223925.493], "main", ["notmodified", "notmodified"]], "181": [[718494.786, 1223920.31], "main", ["notmodified", "notmodified"]], "182": [[718484.795, 1223919.68], "main", ["notmodified", "notmodified"]], "183": [[718474.798, 1223918.958], "main", ["notmodified", "notmodified"]], "184": [[718464.806, 1223918.328], "main", ["notmodified", "notmodified"]], "185": [[718454.809, 1223917.606], "main", ["notmodified", "notmodified"]], "186": [[718501.82, 1223928.504], "main", ["notmodified", "notmodified"]], "2": [[718517.315, 1223980.347], "main", ["notmodified", "notmodified"]], "3": [[718513.326, 1223964.492], "main", ["notmodified", "notmodified"]], "4": [[718512.111, 1223959.079], "main", ["notmodified", "notmodified"]], "5": [[718507.388, 1223943.175], "main", ["notmodified", "notmodified"]], "51": [[718456.067, 1223989.333], "main", ["notmodified", "notmodified"]], "52": [[718525.164, 1223990.048], "main", ["notmodified", "notmodified"]], "6": [[718506.01, 1223936.492], "main", ["notmodified", "notmodified"]], "7": [[718502.491, 1223920.885], "main", ["notmodified", "notmodified"]], "8": [[718500.578, 1223916.059], "main", ["notmodified", "notmodified"]], "A": [[718460.702, 1224072.472], "main", ["notmodified", "notmodified"]], "B": [[718545.897, 1224076.857], "main", ["notmodified", "notmodified"]], "C": [[718528.637, 1224003.191], "main", ["notmodified", "notmodified"]], "D": [[718451.28, 1223903.462], "main", ["notmodified", "notmodified"]]}, "district": "COIMBATORE", "lines": [{"coordinates": ["A", "D"], "dashes": "[ 30 10 1 3 1 3 1 10 ] 1", "length": 1856, "strokewidth": "1"}, {"coordinates": ["C", "B"], "dashes": "[ 30 10 1 3 1 3 1 10 ] 1", "length": 829.59326, "strokewidth": "1"}, {"coordinates": ["B", "A"], "dashes": "[ 30 10 1 3 1 3 1 10 ] 1", "length": 935.3609, "strokewidth": "1"}, {"coordinates": ["C", "A"], "dashes": "[ 30 10 1 3 1 3 1 10 ] 1", "length": 1063.9009, "strokewidth": "1"}, {"coordinates": ["C", "D"], "dashes": "[ 30 10 1 3 1 3 1 10 ] 1", "length": 1383.8776, "strokewidth": "1"}, {"coordinates": ["132", "167"], "dashes": "[ 9 0 ] 1", "length": 85.58621, "strokewidth": "1"}, {"coordinates": ["167", "168"], "dashes": "[ 9 0 ] 1", "length": 109.89541, "strokewidth": "1"}, {"coordinates": ["168", "133"], "dashes": "[ 9 0 ] 1", "length": 86.70064, "strokewidth": "1"}, {"coordinates": ["133", "132"], "dashes": "[ 9 0 ] 1", "length": 110.76552, "strokewidth": "1"}, {"coordinates": ["131", "166"], "dashes": "[ 9 0 ] 1", "length": 85.47514, "strokewidth": "1"}, {"coordinates": ["166", "167"], "dashes": "[ 9 0 ] 1", "length": 108.779594, "strokewidth": "1"}, {"coordinates": ["167", "132"], "dashes": "[ 9 0 ] 1", "length": 85.58621, "strokewidth": "1"}, {"coordinates": ["132", "131"], "dashes": "[ 9 0 ] 1", "length": 109.77249, "strokewidth": "1"}, {"coordinates": ["118", "163"], "dashes": "[ 9 0 ] 1", "length": 86.70064, "strokewidth": "1"}, {"coordinates": ["163", "103"], "dashes": "[ 9 0 ] 1", "length": 61.400326, "strokewidth": "1"}, {"coordinates": ["103", "102"], "dashes": "[ 9 0 ] 1", "length": 88, "strokewidth": "1"}, {"coordinates": ["102", "118"], "dashes": "[ 9 0 ] 1", "length": 50.24938, "strokewidth": "1"}, {"coordinates": ["120", "161"], "dashes": "[ 9 0 ] 1", "length": 86.70064, "strokewidth": "1"}, {"coordinates": ["161", "162"], "dashes": "[ 9 0 ] 1", "length": 108.66462, "strokewidth": "1"}, {"coordinates": ["162", "119"], "dashes": "[ 9 0 ] 1", "length": 86.70064, "strokewidth": "1"}, {"coordinates": ["119", "120"], "dashes": "[ 9 0 ] 1", "length": 108.66462, "strokewidth": "1"}, {"coordinates": ["162", "125"], "dashes": "[ 9 0 ] 1", "length": 86.833176, "strokewidth": "1"}, {"coordinates": ["125", "124"], "dashes": "[ 9 0 ] 1", "length": 109.65856, "strokewidth": "1"}, {"coordinates": ["124", "163"], "dashes": "[ 9 0 ] 1", "length": 87.823685, "strokewidth": "1"}, {"coordinates": ["163", "162"], "dashes": "[ 9 0 ] 1", "length": 109.55364, "strokewidth": "1"}, {"coordinates": ["133", "168"], "dashes": "[ 9 0 ] 1", "length": 86.70064, "strokewidth": "1"}, {"coordinates": ["168", "169"], "dashes": "[ 9 0 ] 1", "length": 108.779594, "strokewidth": "1"}, {"coordinates": ["169", "134"], "dashes": "[ 9 0 ] 1", "length": 86.833176, "strokewidth": "1"}, {"coordinates": ["134", "133"], "dashes": "[ 9 0 ] 1", "length": 109.77249, "strokewidth": "1"}, {"coordinates": ["119", "162"], "dashes": "[ 9 0 ] 1", "length": 86.70064, "strokewidth": "1"}, {"coordinates": ["162", "163"], "dashes": "[ 9 0 ] 1", "length": 109.55364, "strokewidth": "1"}, {"coordinates": ["163", "118"], "dashes": "[ 9 0 ] 1", "length": 86.70064, "strokewidth": "1"}, {"coordinates": ["118", "119"], "dashes": "[ 9 0 ] 1", "length": 109.55364, "strokewidth": "1"}, {"coordinates": ["122", "159"], "dashes": "[ 9 0 ] 1", "length": 85.84288, "strokewidth": "1"}, {"coordinates": ["159", "160"], "dashes": "[ 9 0 ] 1", "length": 108.66462, "strokewidth": "1"}, {"coordinates": ["160", "121"], "dashes": "[ 9 0 ] 1", "length": 86.833176, "strokewidth": "1"}, {"coordinates": ["121", "122"], "dashes": "[ 9 0 ] 1", "length": 108.55874, "strokewidth": "1"}, {"coordinates": ["159", "128"], "dashes": "[ 9 0 ] 1", "length": 86.833176, "strokewidth": "1"}, {"coordinates": ["128", "127"], "dashes": "[ 9 0 ] 1", "length": 108.66462, "strokewidth": "1"}, {"coordinates": ["127", "160"], "dashes": "[ 9 0 ] 1", "length": 86.833176, "strokewidth": "1"}, {"coordinates": ["160", "159"], "dashes": "[ 9 0 ] 1", "length": 108.66462, "strokewidth": "1"}, {"coordinates": ["130", "164"], "dashes": "[ 9 0 ] 1", "length": 63.28507, "strokewidth": "1"}, {"coordinates": ["164", "165"], "dashes": "[ 9 0 ] 1", "length": 22.203604, "strokewidth": "1"}, {"coordinates": ["165", "166"], "dashes": "[ 9 0 ] 1", "length": 109.77249, "strokewidth": "1"}, {"coordinates": ["166", "131"], "dashes": "[ 9 0 ] 1", "length": 85.47514, "strokewidth": "1"}, {"coordinates": ["131", "130"], "dashes": "[ 9 0 ] 1", "length": 109.77249, "strokewidth": "1"}, {"coordinates": ["165", "140"], "dashes": "[ 9 0 ] 1", "length": 85.37564, "strokewidth": "1"}, {"coordinates": ["140", "139"], "dashes": "[ 9 0 ] 1", "length": 107.78683, "strokewidth": "1"}, {"coordinates": ["139", "166"], "dashes": "[ 9 0 ] 1", "length": 85.58621, "strokewidth": "1"}, {"coordinates": ["166", "165"], "dashes": "[ 9 0 ] 1", "length": 109.77249, "strokewidth": "1"}, {"coordinates": ["121", "160"], "dashes": "[ 9 0 ] 1", "length": 86.833176, "strokewidth": "1"}, {"coordinates": ["160", "161"], "dashes": "[ 9 0 ] 1", "length": 109.55364, "strokewidth": "1"}, {"coordinates": ["161", "120"], "dashes": "[ 9 0 ] 1", "length": 86.70064, "strokewidth": "1"}, {"coordinates": ["120", "121"], "dashes": "[ 9 0 ] 1", "length": 108.55874, "strokewidth": "1"}, {"coordinates": ["123", "158"], "dashes": "[ 9 0 ] 1", "length": 86.833176, "strokewidth": "1"}, {"coordinates": ["158", "159"], "dashes": "[ 9 0 ] 1", "length": 108.55874, "strokewidth": "1"}, {"coordinates": ["159", "122"], "dashes": "[ 9 0 ] 1", "length": 85.84288, "strokewidth": "1"}, {"coordinates": ["122", "123"], "dashes": "[ 9 0 ] 1", "length": 108.66462, "strokewidth": "1"}, {"coordinates": ["51", "A"], "dashes": "[ 9 0 ] 1", "length": 913, "strokewidth": "1"}, {"coordinates": ["A", "B"], "dashes": "[ 9 0 ] 1", "length": 935.3609, "strokewidth": "1"}, {"coordinates": ["B", "C"], "dashes": "[ 9 0 ] 1", "length": 829.59326, "strokewidth": "1"}, {"coordinates": ["C", "52"], "dashes": "[ 9 0 ] 1", "length": 149.05032, "strokewidth": "1"}, {"coordinates": ["158", "129"], "dashes": "[ 9 0 ] 1", "length": 85.98837, "strokewidth": "1"}, {"coordinates": ["129", "128"], "dashes": "[ 9 0 ] 1", "length": 109.65856, "strokewidth": "1"}, {"coordinates": ["128", "159"], "dashes": "[ 9 0 ] 1", "length": 86.833176, "strokewidth": "1"}, {"coordinates": ["159", "158"], "dashes": "[ 9 0 ] 1", "length": 108.55874, "strokewidth": "1"}, {"coordinates": ["160", "127"], "dashes": "[ 9 0 ] 1", "length": 86.833176, "strokewidth": "1"}, {"coordinates": ["127", "126"], "dashes": "[ 9 0 ] 1", "length": 109.55364, "strokewidth": "1"}, {"coordinates": ["126", "161"], "dashes": "[ 9 0 ] 1", "length": 86.833176, "strokewidth": "1"}, {"coordinates": ["161", "160"], "dashes": "[ 9 0 ] 1", "length": 109.55364, "strokewidth": "1"}, {"coordinates": ["163", "124"], "dashes": "[ 9 0 ] 1", "length": 87.823685, "strokewidth": "1"}, {"coordinates": ["124", "104"], "dashes": "[ 9 0 ] 1", "length": 73.43705, "strokewidth": "1"}, {"coordinates": ["104", "103"], "dashes": "[ 9 0 ] 1", "length": 88, "strokewidth": "1"}, {"coordinates": ["103", "163"], "dashes": "[ 9 0 ] 1", "length": 61.400326, "strokewidth": "1"}, {"coordinates": ["174", "173"], "dashes": "[ 9 0 ] 1", "length": 109.77249, "strokewidth": "1"}, {"coordinates": ["173", "172"], "dashes": "[ 9 0 ] 1", "length": 109.65856, "strokewidth": "1"}, {"coordinates": ["172", "171"], "dashes": "[ 9 0 ] 1", "length": 110.76552, "strokewidth": "1"}, {"coordinates": ["171", "152"], "dashes": "[ 9 0 ] 1", "length": 109.65856, "strokewidth": "1"}, {"coordinates": ["152", "151"], "dashes": "[ 9 0 ] 1", "length": 88.56636, "strokewidth": "1"}, {"coordinates": ["151", "6"], "dashes": "[ 9 0 ] 1", "length": 50.358715, "strokewidth": "1"}, {"coordinates": ["6", "175"], "dashes": "[ 9 0 ] 1", "length": 88.11924, "strokewidth": "1"}, {"coordinates": ["175", "7"], "dashes": "[ 9 0 ] 1", "length": 87.29834, "strokewidth": "1"}, {"coordinates": ["7", "181"], "dashes": "[ 9 0 ] 1", "length": 84.71718, "strokewidth": "1"}, {"coordinates": ["181", "182"], "dashes": "[ 9 0 ] 1", "length": 109.77249, "strokewidth": "1"}, {"coordinates": ["182", "183"], "dashes": "[ 9 0 ] 1", "length": 109.89541, "strokewidth": "1"}, {"coordinates": ["183", "184"], "dashes": "[ 9 0 ] 1", "length": 109.77249, "strokewidth": "1"}, {"coordinates": ["184", "185"], "dashes": "[ 9 0 ] 1", "length": 109.89541, "strokewidth": "1"}, {"coordinates": ["185", "110"], "dashes": "[ 9 0 ] 1", "length": 30.265491, "strokewidth": "1"}, {"coordinates": ["110", "111"], "dashes": "[ 9 0 ] 1", "length": 66, "strokewidth": "1"}, {"coordinates": ["111", "157"], "dashes": "[ 9 0 ] 1", "length": 37.48333, "strokewidth": "1"}, {"coordinates": ["157", "156"], "dashes": "[ 9 0 ] 1", "length": 109.32977, "strokewidth": "1"}, {"coordinates": ["156", "155"], "dashes": "[ 9 0 ] 1", "length": 109.17875, "strokewidth": "1"}, {"coordinates": ["155", "154"], "dashes": "[ 9 0 ] 1", "length": 109.17875, "strokewidth": "1"}, {"coordinates": ["154", "153"], "dashes": "[ 9 0 ] 1", "length": 109.32977, "strokewidth": "1"}, {"coordinates": ["153", "8"], "dashes": "[ 9 0 ] 1", "length": 63.63961, "strokewidth": "1"}, {"coordinates": ["8", "117"], "dashes": "[ 9 0 ] 1", "length": 86.492775, "strokewidth": "1"}, {"coordinates": ["117", "1"], "dashes": "[ 9 0 ] 1", "length": 54.589375, "strokewidth": "1"}, {"coordinates": ["1", "52"], "dashes": "[ 9 0 ] 1", "length": 920.9777, "strokewidth": "1"}, {"coordinates": ["52", "101"], "dashes": "[ 9 0 ] 1", "length": 764.69666, "strokewidth": "1"}, {"coordinates": ["101", "102"], "dashes": "[ 9 0 ] 1", "length": 66, "strokewidth": "1"}, {"coordinates": ["102", "118"], "dashes": "[ 9 0 ] 1", "length": 50.24938, "strokewidth": "1"}, {"coordinates": ["118", "119"], "dashes": "[ 9 0 ] 1", "length": 109.55364, "strokewidth": "1"}, {"coordinates": ["119", "120"], "dashes": "[ 9 0 ] 1", "length": 108.66462, "strokewidth": "1"}, {"coordinates": ["120", "121"], "dashes": "[ 9 0 ] 1", "length": 108.55874, "strokewidth": "1"}, {"coordinates": ["121", "122"], "dashes": "[ 9 0 ] 1", "length": 108.55874, "strokewidth": "1"}, {"coordinates": ["122", "123"], "dashes": "[ 9 0 ] 1", "length": 108.66462, "strokewidth": "1"}, {"coordinates": ["123", "2"], "dashes": "[ 9 0 ] 1", "length": 85.37564, "strokewidth": "1"}, {"coordinates": ["2", "3"], "dashes": "[ 9 0 ] 1", "length": 179.25401, "strokewidth": "1"}, {"coordinates": ["3", "129"], "dashes": "[ 9 0 ] 1", "length": 26.172504, "strokewidth": "1"}, {"coordinates": ["129", "128"], "dashes": "[ 9 0 ] 1", "length": 109.65856, "strokewidth": "1"}, {"coordinates": ["128", "127"], "dashes": "[ 9 0 ] 1", "length": 108.66462, "strokewidth": "1"}, {"coordinates": ["127", "126"], "dashes": "[ 9 0 ] 1", "length": 109.55364, "strokewidth": "1"}, {"coordinates": ["126", "125"], "dashes": "[ 9 0 ] 1", "length": 108.66462, "strokewidth": "1"}, {"coordinates": ["125", "124"], "dashes": "[ 9 0 ] 1", "length": 109.65856, "strokewidth": "1"}, {"coordinates": ["124", "104"], "dashes": "[ 9 0 ] 1", "length": 73.43705, "strokewidth": "1"}, {"coordinates": ["104", "105"], "dashes": "[ 9 0 ] 1", "length": 66, "strokewidth": "1"}, {"coordinates": ["105", "134"], "dashes": "[ 9 0 ] 1", "length": 82.607506, "strokewidth": "1"}, {"coordinates": ["134", "133"], "dashes": "[ 9 0 ] 1", "length": 109.77249, "strokewidth": "1"}, {"coordinates": ["133", "132"], "dashes": "[ 9 0 ] 1", "length": 110.76552, "strokewidth": "1"}, {"coordinates": ["132", "131"], "dashes": "[ 9 0 ] 1", "length": 109.77249, "strokewidth": "1"}, {"coordinates": ["131", "130"], "dashes": "[ 9 0 ] 1", "length": 109.77249, "strokewidth": "1"}, {"coordinates": ["130", "4"], "dashes": "[ 9 0 ] 1", "length": 113.86395, "strokewidth": "1"}, {"coordinates": ["4", "135"], "dashes": "[ 9 0 ] 1", "length": 67.911705, "strokewidth": "1"}, {"coordinates": ["135", "5"], "dashes": "[ 9 0 ] 1", "length": 114.00439, "strokewidth": "1"}, {"coordinates": ["5", "140"], "dashes": "[ 9 0 ] 1", "length": 54.451813, "strokewidth": "1"}, {"coordinates": ["140", "139"], "dashes": "[ 9 0 ] 1", "length": 107.78683, "strokewidth": "1"}, {"coordinates": ["139", "138"], "dashes": "[ 9 0 ] 1", "length": 108.903625, "strokewidth": "1"}, {"coordinates": ["138", "137"], "dashes": "[ 9 0 ] 1", "length": 108.779594, "strokewidth": "1"}, {"coordinates": ["137", "136"], "dashes": "[ 9 0 ] 1", "length": 108.903625, "strokewidth": "1"}, {"coordinates": ["136", "107"], "dashes": "[ 9 0 ] 1", "length": 105.801704, "strokewidth": "1"}, {"coordinates": ["107", "108"], "dashes": "[ 9 0 ] 1", "length": 66, "strokewidth": "1"}, {"coordinates": ["4", "135"], "dashes": "[ 9 0 ] 1", "length": 67.911705, "strokewidth": "1"}, {"coordinates": ["135", "164"], "dashes": "[ 9 0 ] 1", "length": 91.66242, "strokewidth": "1"}, {"coordinates": ["164", "130"], "dashes": "[ 9 0 ] 1", "length": 63.28507, "strokewidth": "1"}, {"coordinates": ["130", "4"], "dashes": "[ 9 0 ] 1", "length": 113.86395, "strokewidth": "1"}, {"coordinates": ["135", "5"], "dashes": "[ 9 0 ] 1", "length": 114.00439, "strokewidth": "1"}, {"coordinates": ["5", "140"], "dashes": "[ 9 0 ] 1", "length": 54.451813, "strokewidth": "1"}, {"coordinates": ["140", "165"], "dashes": "[ 9 0 ] 1", "length": 85.37564, "strokewidth": "1"}, {"coordinates": ["165", "164"], "dashes": "[ 9 0 ] 1", "length": 22.203604, "strokewidth": "1"}, {"coordinates": ["164", "135"], "dashes": "[ 9 0 ] 1", "length": 91.66242, "strokewidth": "1"}, {"coordinates": ["101", "52"], "dashes": "[ 9 0 ] 1", "length": 764.69666, "strokewidth": "1"}, {"coordinates": ["2", "3"], "dashes": "[ 9 0 ] 1", "length": 179.25401, "strokewidth": "1"}, {"coordinates": ["3", "129"], "dashes": "[ 9 0 ] 1", "length": 26.172504, "strokewidth": "1"}, {"coordinates": ["129", "158"], "dashes": "[ 9 0 ] 1", "length": 85.98837, "strokewidth": "1"}, {"coordinates": ["158", "123"], "dashes": "[ 9 0 ] 1", "length": 86.833176, "strokewidth": "1"}, {"coordinates": ["123", "2"], "dashes": "[ 9 0 ] 1", "length": 85.37564, "strokewidth": "1"}, {"coordinates": ["161", "126"], "dashes": "[ 9 0 ] 1", "length": 86.833176, "strokewidth": "1"}, {"coordinates": ["126", "125"], "dashes": "[ 9 0 ] 1", "length": 108.66462, "strokewidth": "1"}, {"coordinates": ["125", "162"], "dashes": "[ 9 0 ] 1", "length": 86.833176, "strokewidth": "1"}, {"coordinates": ["162", "161"], "dashes": "[ 9 0 ] 1", "length": 108.66462, "strokewidth": "1"}, {"coordinates": ["A", "B"], "dashes": "[ 9 0 ] 1", "length": 935.3609, "strokewidth": "3"}, {"coordinates": ["B", "C"], "dashes": "[ 9 0 ] 1", "length": 829.59326, "strokewidth": "3"}, {"coordinates": ["51", "A"], "dashes": "[ 9 0 ] 1", "length": 913, "strokewidth": "3"}, {"coordinates": ["C", "52"], "dashes": "[ 9 0 ] 1", "length": 149.05032, "strokewidth": "3"}, {"coordinates": ["52", "1"], "dashes": "[ 9 0 ] 1", "length": 920.9777, "strokewidth": "3"}, {"coordinates": ["101", "51"], "dashes": "[ 9 0 ] 1", "length": 65, "strokewidth": "3"}, {"coordinates": ["102", "101"], "dashes": "[ 9 0 ] 1", "length": 66, "strokewidth": "3"}, {"coordinates": ["103", "102"], "dashes": "[ 9 0 ] 1", "length": 88, "strokewidth": "3"}, {"coordinates": ["104", "103"], "dashes": "[ 9 0 ] 1", "length": 88, "strokewidth": "3"}, {"coordinates": ["105", "104"], "dashes": "[ 9 0 ] 1", "length": 66, "strokewidth": "3"}, {"coordinates": ["106", "105"], "dashes": "[ 9 0 ] 1", "length": 87, "strokewidth": "3"}, {"coordinates": ["107", "106"], "dashes": "[ 9 0 ] 1", "length": 88, "strokewidth": "3"}, {"coordinates": ["108", "107"], "dashes": "[ 9 0 ] 1", "length": 66, "strokewidth": "3"}, {"coordinates": ["109", "108"], "dashes": "[ 9 0 ] 1", "length": 88, "strokewidth": "3"}, {"coordinates": ["110", "109"], "dashes": "[ 9 0 ] 1", "length": 88, "strokewidth": "3"}, {"coordinates": ["D", "111"], "dashes": "[ 9 0 ] 1", "length": 87, "strokewidth": "3"}, {"coordinates": ["111", "110"], "dashes": "[ 9 0 ] 1", "length": 66, "strokewidth": "3"}, {"coordinates": ["112", "D"], "dashes": "[ 9 0 ] 1", "length": 49.648766, "strokewidth": "3"}, {"coordinates": ["113", "112"], "dashes": "[ 9 0 ] 1", "length": 109.32977, "strokewidth": "3"}, {"coordinates": ["114", "113"], "dashes": "[ 9 0 ] 1", "length": 109.32977, "strokewidth": "3"}, {"coordinates": ["115", "114"], "dashes": "[ 9 0 ] 1", "length": 109.48972, "strokewidth": "3"}, {"coordinates": ["116", "115"], "dashes": "[ 9 0 ] 1", "length": 109.32977, "strokewidth": "3"}, {"coordinates": ["1", "117"], "dashes": "[ 9 0 ] 1", "length": 54.589375, "strokewidth": "3"}, {"coordinates": ["117", "116"], "dashes": "[ 9 0 ] 1", "length": 35.510563, "strokewidth": "3"}], "subdivision_list": {"1": [[718489.762, 1224023.536], ["51", "A", "B", "C", "52"], 6537.538682888], "10": [[718513.616, 1223972.971], ["2", "3", "129", "158", "123", "2"], 80.29768952206359], "11": [[718504.827, 1223967.706], ["158", "129", "128", "159", "158"], 78.35959850237123], "12": [[718496.49, 1223967.258], ["159", "128", "127", "160", "159"], 78.4552553552785], "13": [[718486.038, 1223966.562], ["160", "127", "126", "161", "160"], 79.07078640875989], "14": [[718476.066, 1223966.295], ["161", "126", "125", "162", "161"], 78.45525535524939], "15": [[718466.697, 1223965.356], ["162", "125", "124", "163", "162"], 79.57402463493054], "16": [[718457.626, 1223964.857], ["163", "124", "104", "103", "163"], 49.13850943717989], "18": [[718467.65, 1223951.327], ["133", "168", "169", "134", "133"], 78.85867773491191], "19": [[718476.959, 1223952.818], ["132", "167", "168", "133", "132"], 79.05415043435642], "2": [[718491.722, 1223981.682], ["174", "173", "172", "171", "152", "151", "6", "175", "7", "181", "182", "183", "184", "185", "110", "111", "157", "156", "155", "154", "153", "8", "117", "1", "52", "101", "102", "118", "119", "120", "121", "122", "123", "2", "3", "129", "128", "127", "126", "125", "124", "104", "105", "134", "133", "132", "131", "130", "4", "135", "5", "140", "139", "138", "137", "136", "107", "108"], 1808.8336574626155], "20": [[718486.101, 1223952.948], ["131", "166", "167", "132", "131"], 77.73990845531807], "21": [[718496.533, 1223953.28], ["130", "164", "165", "166", "131", "130"], 77.8022933593893], "22": [[718506.96, 1223955.165], ["4", "135", "164", "130", "4"], 54.20416364748962], "23": [[718504.93, 1223948.244], ["135", "5", "140", "165", "164", "135"], 64.84286928773508], "24": [[718496.349, 1223946.713], ["165", "140", "139", "166", "165"], 77.33232708205469], "3": [[718467.779, 1223986.396], ["101", "52"], 0.0], "4": [[718457.44, 1223972.997], ["118", "163", "103", "102", "118"], 40.43789481653948], "5": [[718464.427, 1223973.795], ["119", "162", "163", "118", "119"], 78.97928854942438], "6": [[718474.464, 1223973.601], ["120", "161", "162", "119", "120"], 78.35543950882857], "7": [[718484.552, 1223974.317], ["121", "160", "161", "120", "121"], 78.66736402906827], "8": [[718495.687, 1223974.153], ["122", "159", "160", "121", "122"], 77.95617612276692], "9": [[718504.975, 1223975.28], ["123", "158", "159", "122", "123"], 77.95617612276692]}, "survey_no": "258", "taluk": "Coimbatore North", "village": "Saravanampatty.", "Areass": [], "srt_coordinetes": ["A", "B", "C", "D", "1", "2", "3", "4", "5", "6", "7", "8", "51", "52", "101", "102", "103", "104", "105", "106", "107", "108", "109", "110", "111", "112", "113", "114", "115", "116", "117", "118", "119", "120", "121", "122", "123", "124", "125", "126", "127", "128", "129", "130", "131", "132", "133", "134", "135", "136", "137", "138", "139", "140", "151", "152", "153", "154", "155", "156", "157", "158", "159", "160", "161", "162", "163", "164", "165", "166", "167", "168", "169", "171", "172", "173", "174", "175", "176", "177", "178", "179", "180", "181", "182", "183", "184", "185", "186"]}