{"Scale": "1:700", "coordinates": {"1": [[180763.17, 1342573.625], "main", ["notmodified", "notmodified"]], "3": [[180849.578, 1342216.246], "main", ["notmodified", "notmodified"]], "4": [[180816.736, 1342376.606], "main", ["notmodified", "notmodified"]], "5": [[180802.852, 1342439.203], "main", ["notmodified", "notmodified"]], "6": [[180818.37, 1342290.097], "main", ["notmodified", "notmodified"]], "A": [[180924.34, 1342112.082], "main", ["notmodified", "notmodified"]], "B": [[180839.064, 1342397.99], "main", ["notmodified", "notmodified"]], "C": [[180922.122, 1342126.981], "main", ["notmodified", "notmodified"]], "D": [[180882.717, 1342167.886], "main", ["notmodified", "notmodified"]], "E": [[180837.166, 1342256.118], "main", ["notmodified", "notmodified"]], "F": [[180792.265, 1342519.547], "main", ["notmodified", "notmodified"]], "G": [[180791.34, 1342613.329], "main", ["notmodified", "notmodified"]], "H": [[180759.843, 1342639.84], "main", ["notmodified", "notmodified"]], "J": [[180829.099, 1342215.178], "main", ["notmodified", "notmodified"]], "K": [[180840.085, 1342203.684], "main", ["notmodified", "notmodified"]], "L": [[180817.534, 1342318.99], "main", ["notmodified", "notmodified"]], "t0": [[180774.877, 1342495.092], "main", ["notmodified", "notmodified"]]}, "district": "DHARMAPURI", "lines": [{"coordinates": ["A", "B"], "dashes": "[ 9 0 ] 1", "length": 34.20526, "strokewidth": "3"}, {"coordinates": ["B", "C"], "dashes": "[ 9 0 ] 1", "length": 53.14132, "strokewidth": "3"}, {"coordinates": ["C", "D"], "dashes": "[ 9 0 ] 1", "length": 229.53214, "strokewidth": "3"}, {"coordinates": ["D", "3"], "dashes": "[ 9 0 ] 1", "length": 236.91348, "strokewidth": "3"}, {"coordinates": ["3", "E"], "dashes": "[ 9 0 ] 1", "length": 168.76018, "strokewidth": "3"}, {"coordinates": ["E", "4"], "dashes": "[ 9 0 ] 1", "length": 493.8674, "strokewidth": "3"}, {"coordinates": ["4", "F"], "dashes": "[ 9 0 ] 1", "length": 586.0589, "strokewidth": "3"}, {"coordinates": ["F", "G"], "dashes": "[ 9 0 ] 1", "length": 379.01187, "strokewidth": "3"}, {"coordinates": ["G", "H"], "dashes": "[ 9 0 ] 1", "length": 166.37308, "strokewidth": "3"}, {"coordinates": ["H", "1"], "dashes": "[ 9 0 ] 1", "length": 267.92722, "strokewidth": "3"}, {"coordinates": ["1", "t0"], "dashes": "[ 9 0 ] 1", "length": 320.87692, "strokewidth": "3"}, {"coordinates": ["t0", "5"], "dashes": "[ 9 0 ] 1", "length": 252.57277, "strokewidth": "3"}, {"coordinates": ["5", "L"], "dashes": "[ 9 0 ] 1", "length": 489.41803, "strokewidth": "3"}, {"coordinates": ["L", "6"], "dashes": "[ 9 0 ] 1", "length": 116.81181, "strokewidth": "3"}, {"coordinates": ["6", "J"], "dashes": "[ 9 0 ] 1", "length": 305.85126, "strokewidth": "3"}, {"coordinates": ["J", "K"], "dashes": "[ 9 0 ] 1", "length": 64.25729, "strokewidth": "3"}, {"coordinates": ["K", "A"], "dashes": "[ 9 0 ] 1", "length": 502.96124, "strokewidth": "3"}, {"coordinates": ["G", "B"], "dashes": "[ 30 10 1 3 1 3 1 10 ] 1", "length": 2082.5476, "strokewidth": "2"}, {"coordinates": ["F", "E"], "dashes": "[ 30 10 1 3 1 3 1 10 ] 1", "length": 1079.9259, "strokewidth": "2"}, {"coordinates": ["t0", "L"], "dashes": "[ 30 10 1 3 1 3 1 10 ] 1", "length": 732.2465, "strokewidth": "2"}, {"coordinates": ["L", "J"], "dashes": "[ 30 10 1 3 1 3 1 10 ] 1", "length": 422.12085, "strokewidth": "2"}], "subdivision_list": {}, "survey_no": "48", "taluk": "Nallampalli", "village": "Nattahalli", "Areass": [], "srt_coordinetes": ["A", "B", "C", "D", "E", "F", "G", "H", "J", "K", "L", "t0", "1", "3", "4", "5", "6"]}